{"class": "Pose", "topic_name": "/groundtruth", "timestamp": "1739885556.23477", "message": {"position": {"x": 0.30006791557067314, "y": 0.29999999917950465, "z": 0.07383589178640393}, "orientation": {"x": -0.0, "y": 0.0, "z": 8.048749559135008e-10, "w": -1.0}}}
{"class": "Vector3Stamped", "topic_name": "/true_wheel_speeds", "timestamp": "1739885556.235772", "message": {"header": {"seq": 0, "stamp": 0.29814600944519043, "frame_id": ""}, "vector": {"x": 0.0, "y": 0.0, "z": 0.0}}}
{"class": "Pose", "topic_name": "/groundtruth", "timestamp": "1739885556.326283", "message": {"position": {"x": 0.30006791556179957, "y": 0.29999999917947456, "z": 0.07383589179087324}, "orientation": {"x": -0.0, "y": 0.0, "z": 8.04874511824291e-10, "w": -1.0}}}
{"class": "Vector3Stamped", "topic_name": "/true_wheel_speeds", "timestamp": "1739885556.327283", "message": {"header": {"seq": 0, "stamp": 0.39116406440734863, "frame_id": ""}, "vector": {"x": 0.0, "y": 0.0, "z": 0.0}}}
{"class": "Pose", "topic_name": "/groundtruth", "timestamp": "1739885556.399937", "message": {"position": {"x": 0.3000679155608931, "y": 0.29999999917946873, "z": 0.07383589179130456}, "orientation": {"x": -0.0, "y": 0.0, "z": 8.04874511824291e-10, "w": -1.0}}}
{"class": "Vector3Stamped", "topic_name": "/true_wheel_speeds", "timestamp": "1739885556.399937", "message": {"header": {"seq": 0, "stamp": 0.46481800079345703, "frame_id": ""}, "vector": {"x": 0.0, "y": 0.0, "z": 0.0}}}
{"class": "Pose", "topic_name": "/groundtruth", "timestamp": "1739885556.485055", "message": {"position": {"x": 0.3000679155623945, "y": 0.2999999991794744, "z": 0.0738358917904178}, "orientation": {"x": -0.0, "y": 0.0, "z": 8.04874511824291e-10, "w": -1.0}}}
{"class": "Vector3Stamped", "topic_name": "/true_wheel_speeds", "timestamp": "1739885556.485055", "message": {"header": {"seq": 0, "stamp": 0.5489301681518555, "frame_id": ""}, "vector": {"x": 0.0, "y": 0.0, "z": 0.0}}}
{"class": "Pose", "topic_name": "/groundtruth", "timestamp": "1739885556.575332", "message": {"position": {"x": 0.30006791556241075, "y": 0.29999999917947506, "z": 0.0738358917904069}, "orientation": {"x": -0.0, "y": 0.0, "z": 8.04874511824291e-10, "w": -1.0}}}
{"class": "Vector3Stamped", "topic_name": "/true_wheel_speeds", "timestamp": "1739885556.576332", "message": {"header": {"seq": 0, "stamp": 0.6402130126953125, "frame_id": ""}, "vector": {"x": 0.0, "y": 0.0, "z": 0.0}}}
{"class": "Pose", "topic_name": "/groundtruth", "timestamp": "1739885556.649589", "message": {"position": {"x": 0.30006791556216816, "y": 0.299999999179474, "z": 0.07383589179054795}, "orientation": {"x": -0.0, "y": 0.0, "z": 8.04874511824291e-10, "w": -1.0}}}
{"class": "Vector3Stamped", "topic_name": "/true_wheel_speeds", "timestamp": "1739885556.650589", "message": {"header": {"seq": 0, "stamp": 0.7144701480865479, "frame_id": ""}, "vector": {"x": 0.0, "y": 0.0, "z": 0.0}}}
{"class": "Pose", "topic_name": "/groundtruth", "timestamp": "1739885556.734144", "message": {"position": {"x": 0.3000679155621864, "y": 0.29999999917947395, "z": 0.07383589179053732}, "orientation": {"x": -0.0, "y": 0.0, "z": 8.04874511824291e-10, "w": -1.0}}}
{"class": "Vector3Stamped", "topic_name": "/true_wheel_speeds", "timestamp": "1739885556.734144", "message": {"header": {"seq": 0, "stamp": 0.7980270385742188, "frame_id": ""}, "vector": {"x": 0.0, "y": 0.0, "z": 0.0}}}
{"class": "Pose", "topic_name": "/groundtruth", "timestamp": "1739885556.826654", "message": {"position": {"x": 0.3000679155622239, "y": 0.2999999991794741, "z": 0.07383589179051553}, "orientation": {"x": -0.0, "y": 0.0, "z": 8.04874511824291e-10, "w": -1.0}}}
{"class": "Vector3Stamped", "topic_name": "/true_wheel_speeds", "timestamp": "1739885556.827654", "message": {"header": {"seq": 0, "stamp": 0.8905329704284668, "frame_id": ""}, "vector": {"x": 0.0, "y": 0.0, "z": 0.0}}}
{"class": "Pose", "topic_name": "/groundtruth", "timestamp": "1739885556.899434", "message": {"position": {"x": 0.3000679155622177, "y": 0.2999999991794741, "z": 0.07383589179051905}, "orientation": {"x": -0.0, "y": 0.0, "z": 8.04874511824291e-10, "w": -1.0}}}
{"class": "Vector3Stamped", "topic_name": "/true_wheel_speeds", "timestamp": "1739885556.899434", "message": {"header": {"seq": 0, "stamp": 0.963325023651123, "frame_id": ""}, "vector": {"x": 0.0, "y": 0.0, "z": 0.0}}}
{"class": "Vector3Stamped", "topic_name": "/true_wheel_speeds", "timestamp": "1739885556.981735", "message": {"header": {"seq": 0, "stamp": 1.0456140041351318, "frame_id": ""}, "vector": {"x": 0.0, "y": 0.0, "z": 0.0}}}
{"class": "PoseStamped", "topic_name": "/aruco", "timestamp": "1739885557.015107", "message": {"header": {"seq": 0, "stamp": 1739885556.981735, "frame_id": ""}, "pose": {"position": {"x": 0.3000679155622142, "y": 0.2999999991794741, "z": 0}, "orientation": {"x": -0.0, "y": 0.0, "z": 8.04874511824291e-10, "w": -1.0}}}}
{"class": "Pose", "topic_name": "/groundtruth", "timestamp": "1739885557.074366", "message": {"position": {"x": 0.3000679155622142, "y": 0.2999999991794741, "z": 0.07383589179052111}, "orientation": {"x": -0.0, "y": 0.0, "z": 8.04874511824291e-10, "w": -1.0}}}
